your_app/__init__.py
your_app/code.py
your_app-0.1.0.dist-info/DESCRIPTION.rst
your_app-0.1.0.dist-info/METADATA
your_app-0.1.0.dist-info/metadata.json
your_app-0.1.0.dist-info/RECORD
your_app-0.1.0.dist-info/top_level.txt
your_app-0.1.0.dist-info/WHEEL
